Workbook
Name DUEDATE: #REF!
Name INVOICENUMBER: Table1[[#All],[Invoice Number]]
Name PONUMBER: Table2[[#All],[PO Number]]
Name POVENDORNAME: Table2[[#All],[Vendor Name]]
Name VendorName: Vendors!$B$1:$B$1048568

Sheet Instructions
A1: Invoice Tracking Guide
A3: Sheet | B3: Purpose | C3: Primary Inputs | D3: Automated Outputs
A4: Dashboard | B4: Executive overview | C4: None | D4: KPIs and charts
A5: Purchase Orders | B5: Listing of all purchase orders and current status | C5: Vendor, PO description, PO amount | D5: Automatically updates purchase order received amount, balance, status
A6: Invoices | B6: Listing of all invoices and current status | C6: PO number, invoice amount, invoice description | D6: Automatically updates invoice received amount, balance, status, aging
A7: Payments | B7: Listing of all payments received | C7: Invoice number, received amount | D7: Provides data to update invoice and purchase order received amount
A8: Vendors | B8: Listing of all vendors | C8: Vendor information | D8: Provides list of all approved vendors for purchase orders
A9: Customer Invoice | B9: Prepopulated customer invoice | C9: Invoice number | D9: Creates an automated customer invoice ready for printing or saving to a file
A12: How to Use
A13: 1. Add or edit approved vendors on Vendors sheet.
A14: 2. Enter and track purchase orders on Purchase Orders sheet. Received amount and balances will update automatically.
A15: 3. Enter and track invoices on Invoices sheet. Due date, paid amount, balance, status, and aging will update automatically.
A16: 4. Enter and track payments on Payments sheet. Information will automatically update invoices and purchase orders.
A17: 5. Create customer invoices on Customer Invoice sheet using dropdown of invoice numbers to automatically populate customer invoice.
A18: 6. View KPIs updated automatically on the Dashboard sheet.
A19: 7. Use password ADMIN to unlock protected columns that are updated automatically.

Sheet Dashboard
A1: Invoice Tracking Dashboard
A3: TOTAL INVOICED | D3: OUTSTANDING BALANCE | F3: OVERDUE BALANCE
A4: =SUM(Invoices!D:D) -> 54847.17 | D4: =SUM(Invoices!J:J) -> 46527.3 | F4: =SUMIFS(Invoices!J:J,Invoices!H:H,"<"&TODAY(),Invoices!J:J,">0") -> 46417.3
A6: OPEN INVOICES | D6: ACTIVE VENDORS | F6: AVG. DAYS OUTSTANDING
A7: =COUNTIFS(Invoices!J:J,">0") -> 16 | D7: =COUNTIF(Vendors!J:J,"Yes") -> 5 | F7: =IFERROR(SUMIFS(Invoices!L:L,Invoices!J:J,">0")/COUNTIFS(Invoices!J:J,">0"),0) -> 70.875
A9: Outstanding Balances | F9: Vendor Spending Summary
A10: Aging Bucket | B10: Balance | F10: Vendor | G10: Sum of Invoice Amount
A11: Current | B11: =SUMIF(Invoices!M:M,A11,Invoices!J:J) -> 110 | F11: ABC Office Supply | G11: 17250.7
A12: 1-30 Days | B12: =SUMIF(Invoices!M:M,A12,Invoices!J:J) -> 21507.96 | F12: Main Technology Services | G12: 8592.06
A13: 31-60 Days | B13: =SUMIF(Invoices!M:M,A13,Invoices!J:J) -> 7393.16 | F13: U Packaging Inc | G13: 10064.12
A14: 61-90 Days | B14: =SUMIF(Invoices!M:M,A14,Invoices!J:J) -> 17516.18 | F14: Water Street LLC | G14: 200
A15: 90+ Days | B15: =SUMIF(Invoices!M:M,A15,Invoices!J:J) -> 0 | F15: XYZ Industrial Parts | G15: 18730.29
F17: Grand Total | G17: 54837.17
A21: Invoice Activity by Month
A22: Month | B22: Invoice Amount
A23: 46023 | B23: =SUMIFS(Invoices!D:D,Invoices!B:B,">="&DATE(2026,1,1),Invoices!B:B,"<"&DATE(2026,2,1)) -> 0
A24: 46054 | B24: =SUMIFS(Invoices!D:D,Invoices!B:B,">="&DATE(2026,2,1),Invoices!B:B,"<"&DATE(2026,3,1)) -> 0
A25: 46082 | B25: =SUMIFS(Invoices!D:D,Invoices!B:B,">="&DATE(2026,3,1),Invoices!B:B,"<"&DATE(2026,4,1)) -> 0
A26: 46113 | B26: =SUMIFS(Invoices!D:D,Invoices!B:B,">="&DATE(2026,4,1),Invoices!B:B,"<"&DATE(2026,5,1)) -> 15127.42
A27: 46143 | B27: =SUMIFS(Invoices!D:D,Invoices!B:B,">="&DATE(2026,5,1),Invoices!B:B,"<"&DATE(2026,6,1)) -> 14721.79
A28: 46174 | B28: =SUMIFS(Invoices!D:D,Invoices!B:B,">="&DATE(2026,6,1),Invoices!B:B,"<"&DATE(2026,7,1)) -> 24787.96
A29: 46204 | B29: =SUMIFS(Invoices!D:D,Invoices!B:B,">="&DATE(2026,7,1),Invoices!B:B,"<"&DATE(2026,8,1)) -> 210
A30: 46235 | B30: =SUMIFS(Invoices!D:D,Invoices!B:B,">="&DATE(2026,8,1),Invoices!B:B,"<"&DATE(2026,9,1)) -> 0
A31: 46266 | B31: =SUMIFS(Invoices!D:D,Invoices!B:B,">="&DATE(2026,9,1),Invoices!B:B,"<"&DATE(2026,10,1)) -> 0
A32: 46296 | B32: =SUMIFS(Invoices!D:D,Invoices!B:B,">="&DATE(2026,10,1),Invoices!B:B,"<"&DATE(2026,11,1)) -> 0
A33: 46327 | B33: =SUMIFS(Invoices!D:D,Invoices!B:B,">="&DATE(2026,11,1),Invoices!B:B,"<"&DATE(2026,12,1)) -> 0
A34: 46357 | B34: =SUMIFS(Invoices!D:D,Invoices!B:B,">="&DATE(2026,12,1),Invoices!B:B,"<"&DATE(2027,1,1)) -> 0

Sheet Purchase Orders
A1: PO Number | B1: PO Date | C1: Vendor Name | D1: Vendor ID | E1: Buyer | F1: Description | G1: PO Amount | H1: Received Amount | I1: Remaining Balance | J1: Status
A2: PO-2026-1001 | B2: 46125 | C2: ABC Office Supply | D2: =IF(C2="","",_xlfn.XLOOKUP(C2,Vendors!B:B,Vendors!A:A)) -> V001 | E2: Morgan Scott | F2: Network support and accessories | G2: 1062.65 | H2: =IF(G2="","",SUMIF(Payments!D:D,A2,Payments!G:G)) -> 0 | I2: =IF(G2="","",G2-H2) -> 1062.65 | J2: =IF(G2="","",IF(I2=0,"Closed","Open")) -> Open
A3: PO-2026-1002 | B3: 46121 | C3: XYZ Industrial Parts | D3: =IF(C3="","",_xlfn.XLOOKUP(C3,Vendors!B:B,Vendors!A:A)) -> V002 | E3: Taylor Davis | F3: Shipping cartons and labels | G3: 925.1 | H3: =IF(G3="","",SUMIF(Payments!D:D,A3,Payments!G:G)) -> 0 | I3: =IF(G3="","",G3-H3) -> 925.1 | J3: =IF(G3="","",IF(I3=0,"Closed","Open")) -> Open
A4: PO-2026-1003 | B4: 46117 | C4: U Packaging Inc | D4: =IF(C4="","",_xlfn.XLOOKUP(C4,Vendors!B:B,Vendors!A:A)) -> V003 | E4: Casey Martin | F4: Replacement conveyor components | G4: 787.55 | H4: =IF(G4="","",SUMIF(Payments!D:D,A4,Payments!G:G)) -> 280 | I4: =IF(G4="","",G4-H4) -> 507.55 | J4: =IF(G4="","",IF(I4=0,"Closed","Open")) -> Open
A5: PO-2026-1004 | B5: 46173 | C5: ABC Office Supply | D5: =IF(C5="","",_xlfn.XLOOKUP(C5,Vendors!B:B,Vendors!A:A)) -> V001 | E5: Morgan Scott | F5: Freight services | G5: 2713.25 | H5: =IF(G5="","",SUMIF(Payments!D:D,A5,Payments!G:G)) -> 2673.7 | I5: =IF(G5="","",G5-H5) -> 39.55 | J5: =IF(G5="","",IF(I5=0,"Closed","Open")) -> Open
A6: PO-2026-1005 | B6: 46129 | C6: Main Technology Services | D6: =IF(C6="","",_xlfn.XLOOKUP(C6,Vendors!B:B,Vendors!A:A)) -> V004 | E6: Jordan Lee | F6: Janitorial supplies | G6: 1200.2 | H6: =IF(G6="","",SUMIF(Payments!D:D,A6,Payments!G:G)) -> 800 | I6: =IF(G6="","",G6-H6) -> 400.2 | J6: =IF(G6="","",IF(I6=0,"Closed","Open")) -> Open
A7: PO-2026-1006 | B7: 46169 | C7: XYZ Industrial Parts | D7: =IF(C7="","",_xlfn.XLOOKUP(C7,Vendors!B:B,Vendors!A:A)) -> V002 | E7: Taylor Davis | F7: Janitorial supplies | G7: 2575.7 | H7: =IF(G7="","",SUMIF(Payments!D:D,A7,Payments!G:G)) -> 1000 | I7: =IF(G7="","",G7-H7) -> 1575.7 | J7: =IF(G7="","",IF(I7=0,"Closed","Open")) -> Open
A8: PO-2026-1007 | B8: 46165 | C8: U Packaging Inc | D8: =IF(C8="","",_xlfn.XLOOKUP(C8,Vendors!B:B,Vendors!A:A)) -> V003 | E8: Casey Martin | F8: Network support and accessories | G8: 2438.15 | H8: =IF(G8="","",SUMIF(Payments!D:D,A8,Payments!G:G)) -> 1500 | I8: =IF(G8="","",G8-H8) -> 938.15 | J8: =IF(G8="","",IF(I8=0,"Closed","Open")) -> Open
A9: PO-2026-1008 | B9: 46221 | C9: ABC Office Supply | D9: =IF(C9="","",_xlfn.XLOOKUP(C9,Vendors!B:B,Vendors!A:A)) -> V001 | E9: Morgan Scott | F9: Utility services | G9: 4363.85 | H9: =IF(G9="","",SUMIF(Payments!D:D,A9,Payments!G:G)) -> 1403.43 | I9: =IF(G9="","",G9-H9) -> 2960.42 | J9: =IF(G9="","",IF(I9=0,"Closed","Open")) -> Open
A10: PO-2026-1009 | B10: 46217 | C10: XYZ Industrial Parts | D10: =IF(C10="","",_xlfn.XLOOKUP(C10,Vendors!B:B,Vendors!A:A)) -> V002 | E10: Taylor Davis | F10: Safety gloves and protective eyewear | G10: 4226.3 | H10: =IF(G10="","",SUMIF(Payments!D:D,A10,Payments!G:G)) -> 562.74 | I10: =IF(G10="","",G10-H10) -> 3663.56 | J10: =IF(G10="","",IF(I10=0,"Closed","Open")) -> Open
A11: PO-2026-1010 | B11: 46230 | C11: Water Street LLC | D11: =IF(C11="","",_xlfn.XLOOKUP(C11,Vendors!B:B,Vendors!A:A)) -> V005 | E11: Joe Jones | F11: Janitorial supplies | G11: 250 | H11: =IF(G11="","",SUMIF(Payments!D:D,A11,Payments!G:G)) -> 100 | I11: =IF(G11="","",G11-H11) -> 150 | J11: =IF(G11="","",IF(I11=0,"Closed","Open")) -> Open
D12: =IF(C12="","",_xlfn.XLOOKUP(C12,Vendors!B:B,Vendors!A:A)) | H12: =IF(G12="","",SUMIF(Payments!D:D,A12,Payments!G:G)) | I12: =IF(G12="","",G12-H12) | J12: =IF(G12="","",IF(I12=0,"Closed","Open"))
H13: =IF(G13="","",SUMIF(Payments!D:D,A13,Payments!G:G))
D14: =IF(C14="","",_xlfn.XLOOKUP(C14,Vendors!B:B,Vendors!A:A)) | H14: =IF(G14="","",SUMIF(Payments!D:D,A14,Payments!G:G)) | I14: =IF(G14="","",G14-H14) | J14: =IF(G14="","",IF(I14=0,"Closed","Open"))
D15: =IF(C15="","",_xlfn.XLOOKUP(C15,Vendors!B:B,Vendors!A:A)) | H15: =IF(G15="","",SUMIF(Payments!D:D,A15,Payments!G:G)) | I15: =IF(G15="","",G15-H15) | J15: =IF(G15="","",IF(I15=0,"Closed","Open"))
D16: =IF(C16="","",_xlfn.XLOOKUP(C16,Vendors!B:B,Vendors!A:A)) | H16: =IF(G16="","",SUMIF(Payments!D:D,A16,Payments!G:G)) | I16: =IF(G16="","",G16-H16) | J16: =IF(G16="","",IF(I16=0,"Closed","Open"))
H17: =IF(G17="","",SUMIF(Payments!D:D,A17,Payments!G:G)) | I17: =IF(G17="","",G17-H17) | J17: =IF(G17="","",IF(I17=0,"Closed","Open"))
D18: =IF(C18="","",_xlfn.XLOOKUP(C18,Vendors!B:B,Vendors!A:A)) | H18: =IF(G18="","",SUMIF(Payments!D:D,A18,Payments!G:G)) | I18: =IF(G18="","",G18-H18) | J18: =IF(G18="","",IF(I18=0,"Closed","Open"))
D19: =IF(C19="","",_xlfn.XLOOKUP(C19,Vendors!B:B,Vendors!A:A)) | H19: =IF(G19="","",SUMIF(Payments!D:D,A19,Payments!G:G)) | I19: =IF(G19="","",G19-H19) | J19: =IF(G19="","",IF(I19=0,"Closed","Open"))
D20: =IF(C20="","",_xlfn.XLOOKUP(C20,Vendors!B:B,Vendors!A:A)) | H20: =IF(G20="","",SUMIF(Payments!D:D,A20,Payments!G:G)) | I20: =IF(G20="","",G20-H20)
D21: =IF(C21="","",_xlfn.XLOOKUP(C21,Vendors!B:B,Vendors!A:A)) | H21: =IF(G21="","",SUMIF(Payments!D:D,A21,Payments!G:G))
D22: =IF(C22="","",_xlfn.XLOOKUP(C22,Vendors!B:B,Vendors!A:A))
D23: =IF(C23="","",_xlfn.XLOOKUP(C23,Vendors!B:B,Vendors!A:A))
D24: =IF(C24="","",_xlfn.XLOOKUP(C24,Vendors!B:B,Vendors!A:A))
D25: =IF(C25="","",_xlfn.XLOOKUP(C25,Vendors!B:B,Vendors!A:A))
D26: =IF(C26="","",_xlfn.XLOOKUP(C26,Vendors!B:B,Vendors!A:A))
D27: =IF(C27="","",_xlfn.XLOOKUP(C27,Vendors!B:B,Vendors!A:A))
D28: =IF(C28="","",_xlfn.XLOOKUP(C28,Vendors!B:B,Vendors!A:A))
D29: =IF(C29="","",_xlfn.XLOOKUP(C29,Vendors!B:B,Vendors!A:A))

Sheet Invoices
A1: Invoice Number | B1: Invoice Date | C1: PO Number | D1: Invoice Amount | E1: Vendor Name | F1: Vendor ID | G1: Net Days Due | H1: Due Date | I1: Paid Amount | J1: Balance | K1: Status | L1: Days Outstanding | M1: Aging Bucket | N1: Approved By | O1: Description
A2: INV-46001 | B2: 46126 | C2: PO-2026-1003 | D2: 702.74 | E2: =IF(C2="","",_xlfn.XLOOKUP(C2,PONUMBER,POVENDORNAME)) -> U Packaging Inc | F2: =IF(E2="","",_xlfn.XLOOKUP(E2,Vendors!B$1:B$1048568,Vendors!A$1:A$1048568)) -> V003 | G2: =IF(D2="","",_xlfn.XLOOKUP(F2,Vendors!A:A,Vendors!G:G)) -> 30 | H2: =IF(B2="","",B2+G2) -> 46156 | I2: =IF(D2="","",SUMIF(Payments!C:C,A2,Payments!G:G)) -> 0 | J2: =IF(D2="","",D2-I2) -> 702.74 | K2: =IF(J2="","",IF(J2<=0,"Paid","Open")) -> Open | L2: =IF(J2="","",IF(J2<=0,0,MAX(0,TODAY()-B2))) -> 104 | M2: =IF(J2="","",(IF(J2<=0,"Paid",IF(TODAY()<=H2,"Current",IF(TODAY()-H2<=30,"1-30 Days",IF(TODAY()-H2<=60,"31-60 Days",IF(TODAY()-H2<=90,"61-90 Days","90+ Days"))))))) -> 61-90 Days | N2: Taylor Davis | O2: Shipping cartons and labels
A3: INV-46002 | B3: 46128 | C3: PO-2026-1004 | D3: 914.11 | E3: =IF(C3="","",_xlfn.XLOOKUP(C3,PONUMBER,POVENDORNAME)) -> ABC Office Supply | F3: =IF(E3="","",_xlfn.XLOOKUP(E3,Vendors!B$1:B$1048568,Vendors!A$1:A$1048568)) -> V001 | G3: =IF(D3="","",_xlfn.XLOOKUP(F3,Vendors!A:A,Vendors!G:G)) -> 30 | H3: =IF(B3="","",B3+G3) -> 46158 | I3: =IF(D3="","",SUMIF(Payments!C:C,A3,Payments!G:G)) -> 491.37 | J3: =IF(D3="","",D3-I3) -> 422.74 | K3: =IF(J3="","",IF(J3<=0,"Paid","Open")) -> Open | L3: =IF(J3="","",IF(J3<=0,0,MAX(0,TODAY()-B3))) -> 102 | M3: =IF(J3="","",(IF(J3<=0,"Paid",IF(TODAY()<=H3,"Current",IF(TODAY()-H3<=30,"1-30 Days",IF(TODAY()-H3<=60,"31-60 Days",IF(TODAY()-H3<=90,"61-90 Days","90+ Days"))))))) -> 61-90 Days | N3: Morgan Scott | O3: Network support and accessories
A4: INV-46003 | B4: 46136 | C4: PO-2026-1008 | D4: 1759.59 | E4: =IF(C4="","",_xlfn.XLOOKUP(C4,PONUMBER,POVENDORNAME)) -> ABC Office Supply | F4: =IF(E4="","",_xlfn.XLOOKUP(E4,Vendors!B$1:B$1048568,Vendors!A$1:A$1048568)) -> V001 | G4: =IF(D4="","",_xlfn.XLOOKUP(F4,Vendors!A:A,Vendors!G:G)) -> 30 | H4: =IF(B4="","",B4+G4) -> 46166 | I4: =IF(D4="","",SUMIF(Payments!C:C,A4,Payments!G:G)) -> 702.74 | J4: =IF(D4="","",D4-I4) -> 1056.85 | K4: =IF(J4="","",IF(J4<=0,"Paid","Open")) -> Open | L4: =IF(J4="","",IF(J4<=0,0,MAX(0,TODAY()-B4))) -> 94 | M4: =IF(J4="","",(IF(J4<=0,"Paid",IF(TODAY()<=H4,"Current",IF(TODAY()-H4<=30,"1-30 Days",IF(TODAY()-H4<=60,"31-60 Days",IF(TODAY()-H4<=90,"61-90 Days","90+ Days"))))))) -> 61-90 Days | N4: Morgan Scott | O4: Utility services
A5: INV-46004 | B5: 46135 | C5: PO-2026-1008 | D5: 700.69 | E5: =IF(C5="","",_xlfn.XLOOKUP(C5,PONUMBER,POVENDORNAME)) -> ABC Office Supply | F5: =IF(E5="","",_xlfn.XLOOKUP(E5,Vendors!B$1:B$1048568,Vendors!A$1:A$1048568)) -> V001 | G5: =IF(D5="","",_xlfn.XLOOKUP(F5,Vendors!A:A,Vendors!G:G)) -> 30 | H5: =IF(B5="","",B5+G5) -> 46165 | I5: =IF(D5="","",SUMIF(Payments!C:C,A5,Payments!G:G)) -> 700.69 | J5: =IF(D5="","",D5-I5) -> 0 | K5: =IF(J5="","",IF(J5<=0,"Paid","Open")) -> Paid | L5: =IF(J5="","",IF(J5<=0,0,MAX(0,TODAY()-B5))) -> 0 | M5: =IF(J5="","",(IF(J5<=0,"Paid",IF(TODAY()<=H5,"Current",IF(TODAY()-H5<=30,"1-30 Days",IF(TODAY()-H5<=60,"31-60 Days",IF(TODAY()-H5<=90,"61-90 Days","90+ Days"))))))) -> Paid | N5: Casey Martin | O5: Utility services
A6: INV-46005 | B6: 46134 | C6: PO-2026-1009 | D6: 1970.96 | E6: =IF(C6="","",_xlfn.XLOOKUP(C6,PONUMBER,POVENDORNAME)) -> XYZ Industrial Parts | F6: =IF(E6="","",_xlfn.XLOOKUP(E6,Vendors!B$1:B$1048568,Vendors!A$1:A$1048568)) -> V002 | G6: =IF(D6="","",_xlfn.XLOOKUP(F6,Vendors!A:A,Vendors!G:G)) -> 45 | H6: =IF(B6="","",B6+G6) -> 46179 | I6: =IF(D6="","",SUMIF(Payments!C:C,A6,Payments!G:G)) -> 562.74 | J6: =IF(D6="","",D6-I6) -> 1408.22 | K6: =IF(J6="","",IF(J6<=0,"Paid","Open")) -> Open | L6: =IF(J6="","",IF(J6<=0,0,MAX(0,TODAY()-B6))) -> 96 | M6: =IF(J6="","",(IF(J6<=0,"Paid",IF(TODAY()<=H6,"Current",IF(TODAY()-H6<=30,"1-30 Days",IF(TODAY()-H6<=60,"31-60 Days",IF(TODAY()-H6<=90,"61-90 Days","90+ Days"))))))) -> 31-60 Days | N6: Jordan Lee | O6: Printed forms and brochures
A7: INV-46006 | B7: 46132 | C7: PO-2026-1009 | D7: 912.06 | E7: =IF(C7="","",_xlfn.XLOOKUP(C7,PONUMBER,POVENDORNAME)) -> XYZ Industrial Parts | F7: =IF(E7="","",_xlfn.XLOOKUP(E7,Vendors!B$1:B$1048568,Vendors!A$1:A$1048568)) -> V002 | G7: =IF(D7="","",_xlfn.XLOOKUP(F7,Vendors!A:A,Vendors!G:G)) -> 45 | H7: =IF(B7="","",B7+G7) -> 46177 | I7: =IF(D7="","",SUMIF(Payments!C:C,A7,Payments!G:G)) -> 0 | J7: =IF(D7="","",D7-I7) -> 912.06 | K7: =IF(J7="","",IF(J7<=0,"Paid","Open")) -> Open | L7: =IF(J7="","",IF(J7<=0,0,MAX(0,TODAY()-B7))) -> 98 | M7: =IF(J7="","",(IF(J7<=0,"Paid",IF(TODAY()<=H7,"Current",IF(TODAY()-H7<=30,"1-30 Days",IF(TODAY()-H7<=60,"31-60 Days",IF(TODAY()-H7<=90,"61-90 Days","90+ Days"))))))) -> 31-60 Days | N7: Taylor Davis | O7: Printed forms and brochures
A8: INV-46007 | B8: 46130 | C8: PO-2026-1007 | D8: 489.32 | E8: =IF(C8="","",_xlfn.XLOOKUP(C8,PONUMBER,POVENDORNAME)) -> U Packaging Inc | F8: =IF(E8="","",_xlfn.XLOOKUP(E8,Vendors!B$1:B$1048568,Vendors!A$1:A$1048568)) -> V003 | G8: =IF(D8="","",_xlfn.XLOOKUP(F8,Vendors!A:A,Vendors!G:G)) -> 30 | H8: =IF(B8="","",B8+G8) -> 46160 | I8: =IF(D8="","",SUMIF(Payments!C:C,A8,Payments!G:G)) -> 0 | J8: =IF(D8="","",D8-I8) -> 489.32 | K8: =IF(J8="","",IF(J8<=0,"Paid","Open")) -> Open | L8: =IF(J8="","",IF(J8<=0,0,MAX(0,TODAY()-B8))) -> 100 | M8: =IF(J8="","",(IF(J8<=0,"Paid",IF(TODAY()<=H8,"Current",IF(TODAY()-H8<=30,"1-30 Days",IF(TODAY()-H8<=60,"31-60 Days",IF(TODAY()-H8<=90,"61-90 Days","90+ Days"))))))) -> 61-90 Days | N8: Jordan Lee | O8: Safety gloves and protective eyewear
A9: INV-46008 | B9: 46122 | C9: PO-2026-1006 | D9: 7677.95 | E9: =IF(C9="","",_xlfn.XLOOKUP(C9,PONUMBER,POVENDORNAME)) -> XYZ Industrial Parts | F9: =IF(E9="","",_xlfn.XLOOKUP(E9,Vendors!B$1:B$1048568,Vendors!A$1:A$1048568)) -> V002 | G9: =IF(D9="","",_xlfn.XLOOKUP(F9,Vendors!A:A,Vendors!G:G)) -> 45 | H9: =IF(B9="","",B9+G9) -> 46167 | I9: =IF(D9="","",SUMIF(Payments!C:C,A9,Payments!G:G)) -> 0 | J9: =IF(D9="","",D9-I9) -> 7677.95 | K9: =IF(J9="","",IF(J9<=0,"Paid","Open")) -> Open | L9: =IF(J9="","",IF(J9<=0,0,MAX(0,TODAY()-B9))) -> 108 | M9: =IF(J9="","",(IF(J9<=0,"Paid",IF(TODAY()<=H9,"Current",IF(TODAY()-H9<=30,"1-30 Days",IF(TODAY()-H9<=60,"31-60 Days",IF(TODAY()-H9<=90,"61-90 Days","90+ Days"))))))) -> 61-90 Days | N9: Morgan Scott | O9: Freight services
A10: INV-46009 | B10: 46153 | C10: PO-2026-1005 | D10: 7466.58 | E10: =IF(C10="","",_xlfn.XLOOKUP(C10,PONUMBER,POVENDORNAME)) -> Main Technology Services | F10: =IF(E10="","",_xlfn.XLOOKUP(E10,Vendors!B$1:B$1048568,Vendors!A$1:A$1048568)) -> V004 | G10: =IF(D10="","",_xlfn.XLOOKUP(F10,Vendors!A:A,Vendors!G:G)) -> 15 | H10: =IF(B10="","",B10+G10) -> 46168 | I10: =IF(D10="","",SUMIF(Payments!C:C,A10,Payments!G:G)) -> 300 | J10: =IF(D10="","",D10-I10) -> 7166.58 | K10: =IF(J10="","",IF(J10<=0,"Paid","Open")) -> Open | L10: =IF(J10="","",IF(J10<=0,0,MAX(0,TODAY()-B10))) -> 77 | M10: =IF(J10="","",(IF(J10<=0,"Paid",IF(TODAY()<=H10,"Current",IF(TODAY()-H10<=30,"1-30 Days",IF(TODAY()-H10<=60,"31-60 Days",IF(TODAY()-H10<=90,"61-90 Days","90+ Days"))))))) -> 61-90 Days | N10: Taylor Davis | O10: Janitorial supplies
A11: INV-46010 | B11: 46151 | C11: PO-2026-1004 | D11: 7255.21 | E11: =IF(C11="","",_xlfn.XLOOKUP(C11,PONUMBER,POVENDORNAME)) -> ABC Office Supply | F11: =IF(E11="","",_xlfn.XLOOKUP(E11,Vendors!B$1:B$1048568,Vendors!A$1:A$1048568)) -> V001 | G11: =IF(D11="","",_xlfn.XLOOKUP(F11,Vendors!A:A,Vendors!G:G)) -> 30 | H11: =IF(B11="","",B11+G11) -> 46181 | I11: =IF(D11="","",SUMIF(Payments!C:C,A11,Payments!G:G)) -> 2182.33 | J11: =IF(D11="","",D11-I11) -> 5072.88 | K11: =IF(J11="","",IF(J11<=0,"Paid","Open")) -> Open | L11: =IF(J11="","",IF(J11<=0,0,MAX(0,TODAY()-B11))) -> 79 | M11: =IF(J11="","",(IF(J11<=0,"Paid",IF(TODAY()<=H11,"Current",IF(TODAY()-H11<=30,"1-30 Days",IF(TODAY()-H11<=60,"31-60 Days",IF(TODAY()-H11<=90,"61-90 Days","90+ Days"))))))) -> 31-60 Days | N11: Casey Martin | O11: Network support and accessories
A12: INV-46011 | B12: 46186 | C12: PO-2026-1003 | D12: 7043.84 | E12: =IF(C12="","",_xlfn.XLOOKUP(C12,PONUMBER,POVENDORNAME)) -> U Packaging Inc | F12: =IF(E12="","",_xlfn.XLOOKUP(E12,Vendors!B$1:B$1048568,Vendors!A$1:A$1048568)) -> V003 | G12: =IF(D12="","",_xlfn.XLOOKUP(F12,Vendors!A:A,Vendors!G:G)) -> 30 | H12: =IF(B12="","",B12+G12) -> 46216 | I12: =IF(D12="","",SUMIF(Payments!C:C,A12,Payments!G:G)) -> 0 | J12: =IF(D12="","",D12-I12) -> 7043.84 | K12: =IF(J12="","",IF(J12<=0,"Paid","Open")) -> Open | L12: =IF(J12="","",IF(J12<=0,0,MAX(0,TODAY()-B12))) -> 44 | M12: =IF(J12="","",(IF(J12<=0,"Paid",IF(TODAY()<=H12,"Current",IF(TODAY()-H12<=30,"1-30 Days",IF(TODAY()-H12<=60,"31-60 Days",IF(TODAY()-H12<=90,"61-90 Days","90+ Days"))))))) -> 1-30 Days | N12: Jordan Lee | O12: Shipping cartons and labels
A13: INV-46012 | B13: 46184 | C13: PO-2026-1002 | D13: 6832.47 | E13: =IF(C13="","",_xlfn.XLOOKUP(C13,PONUMBER,POVENDORNAME)) -> XYZ Industrial Parts | F13: =IF(E13="","",_xlfn.XLOOKUP(E13,Vendors!B$1:B$1048568,Vendors!A$1:A$1048568)) -> V002 | G13: =IF(D13="","",_xlfn.XLOOKUP(F13,Vendors!A:A,Vendors!G:G)) -> 45 | H13: =IF(B13="","",B13+G13) -> 46229 | I13: =IF(D13="","",SUMIF(Payments!C:C,A13,Payments!G:G)) -> 0 | J13: =IF(D13="","",D13-I13) -> 6832.47 | K13: =IF(J13="","",IF(J13<=0,"Paid","Open")) -> Open | L13: =IF(J13="","",IF(J13<=0,0,MAX(0,TODAY()-B13))) -> 46 | M13: =IF(J13="","",(IF(J13<=0,"Paid",IF(TODAY()<=H13,"Current",IF(TODAY()-H13<=30,"1-30 Days",IF(TODAY()-H13<=60,"31-60 Days",IF(TODAY()-H13<=90,"61-90 Days","90+ Days"))))))) -> 1-30 Days | N13: Morgan Scott | O13: Replacement conveyor components
... A19: INV-46018 | B19: 46230 | C19: PO-2026-1010 | D19: 210 | E19: =IF(C19="","",_xlfn.XLOOKUP(C19,PONUMBER,POVENDORNAME)) -> Water Street LLC | F19: =IF(E19="","",_xlfn.XLOOKUP(E19,Vendors!B$1:B$1048568,Vendors!A$1:A$1048568)) -> V005 | G19: =IF(D19="","",_xlfn.XLOOKUP(F19,Vendors!A:A,Vendors!G:G)) -> 30 | H19: =IF(B19="","",B19+G19) -> 46260 | I19: =IF(D19="","",SUMIF(Payments!C:C,A19,Payments!G:G)) -> 100 | J19: =IF(D19="","",D19-I19) -> 110 | K19: =IF(J19="","",IF(J19<=0,"Paid","Open")) -> Open | L19: =IF(J19="","",IF(J19<=0,0,MAX(0,TODAY()-B19))) -> 0 | M19: =IF(J19="","",(IF(J19<=0,"Paid",IF(TODAY()<=H19,"Current",IF(TODAY()-H19<=30,"1-30 Days",IF(TODAY()-H19<=60,"31-60 Days",IF(TODAY()-H19<=90,"61-90 Days","90+ Days"))))))) -> Current | N19: Joe Jones | O19: Janitorial supplies
E20: =IF(C20="","",_xlfn.XLOOKUP(C20,PONUMBER,POVENDORNAME)) | F20: =IF(E20="","",_xlfn.XLOOKUP(E20,Vendors!B$1:B$1048568,Vendors!A$1:A$1048568)) | G20: =IF(D20="","",_xlfn.XLOOKUP(F20,Vendors!A:A,Vendors!G:G)) | H20: =IF(B20="","",B20+G20) | I20: =IF(D20="","",SUMIF(Payments!C:C,A20,Payments!G:G)) | J20: =IF(D20="","",D20-I20) | K20: =IF(J20="","",IF(J20<=0,"Paid","Open")) | L20: =IF(J20="","",IF(J20<=0,0,MAX(0,TODAY()-B20))) | M20: =IF(J20="","",(IF(J20<=0,"Paid",IF(TODAY()<=H20,"Current",IF(TODAY()-H20<=30,"1-30 Days",IF(TODAY()-H20<=60,"31-60 Days",IF(TODAY()-H20<=90,"61-90 Days","90+ Days")))))))
E21: =IF(C21="","",_xlfn.XLOOKUP(C21,PONUMBER,POVENDORNAME)) | F21: =IF(E21="","",_xlfn.XLOOKUP(E21,Vendors!B$1:B$1048568,Vendors!A$1:A$1048568)) | G21: =IF(D21="","",_xlfn.XLOOKUP(F21,Vendors!A:A,Vendors!G:G)) | H21: =IF(B21="","",B21+G21) | I21: =IF(D21="","",SUMIF(Payments!C:C,A21,Payments!G:G)) | J21: =IF(D21="","",D21-I21) | K21: =IF(J21="","",IF(J21<=0,"Paid","Open")) | L21: =IF(J21="","",IF(J21<=0,0,MAX(0,TODAY()-B21))) | M21: =IF(J21="","",(IF(J21<=0,"Paid",IF(TODAY()<=H21,"Current",IF(TODAY()-H21<=30,"1-30 Days",IF(TODAY()-H21<=60,"31-60 Days",IF(TODAY()-H21<=90,"61-90 Days","90+ Days")))))))
E22: =IF(C22="","",_xlfn.XLOOKUP(C22,PONUMBER,POVENDORNAME)) | F22: =IF(E22="","",_xlfn.XLOOKUP(E22,Vendors!B$1:B$1048568,Vendors!A$1:A$1048568)) | G22: =IF(D22="","",_xlfn.XLOOKUP(F22,Vendors!A:A,Vendors!G:G)) | H22: =IF(B22="","",B22+G22) | I22: =IF(D22="","",SUMIF(Payments!C:C,A22,Payments!G:G)) | J22: =IF(D22="","",D22-I22) | K22: =IF(J22="","",IF(J22<=0,"Paid","Open")) | L22: =IF(J22="","",IF(J22<=0,0,MAX(0,TODAY()-B22))) | M22: =IF(J22="","",(IF(J22<=0,"Paid",IF(TODAY()<=H22,"Current",IF(TODAY()-H22<=30,"1-30 Days",IF(TODAY()-H22<=60,"31-60 Days",IF(TODAY()-H22<=90,"61-90 Days","90+ Days")))))))
E23: =IF(C23="","",_xlfn.XLOOKUP(C23,PONUMBER,POVENDORNAME)) | F23: =IF(E23="","",_xlfn.XLOOKUP(E23,Vendors!B$1:B$1048568,Vendors!A$1:A$1048568)) | G23: =IF(D23="","",_xlfn.XLOOKUP(F23,Vendors!A:A,Vendors!G:G)) | H23: =IF(B23="","",B23+G23) | I23: =IF(D23="","",SUMIF(Payments!C:C,A23,Payments!G:G)) | J23: =IF(D23="","",D23-I23) | K23: =IF(J23="","",IF(J23<=0,"Paid","Open")) | L23: =IF(J23="","",IF(J23<=0,0,MAX(0,TODAY()-B23))) | M23: =IF(J23="","",(IF(J23<=0,"Paid",IF(TODAY()<=H23,"Current",IF(TODAY()-H23<=30,"1-30 Days",IF(TODAY()-H23<=60,"31-60 Days",IF(TODAY()-H23<=90,"61-90 Days","90+ Days")))))))
E24: =IF(C24="","",_xlfn.XLOOKUP(C24,PONUMBER,POVENDORNAME)) | F24: =IF(E24="","",_xlfn.XLOOKUP(E24,Vendors!B$1:B$1048568,Vendors!A$1:A$1048568)) | G24: =IF(D24="","",_xlfn.XLOOKUP(F24,Vendors!A:A,Vendors!G:G)) | H24: =IF(B24="","",B24+G24) | I24: =IF(D24="","",SUMIF(Payments!C:C,A24,Payments!G:G)) | J24: =IF(D24="","",D24-I24) | K24: =IF(J24="","",IF(J24<=0,"Paid","Open")) | L24: =IF(J24="","",IF(J24<=0,0,MAX(0,TODAY()-B24))) | M24: =IF(J24="","",(IF(J24<=0,"Paid",IF(TODAY()<=H24,"Current",IF(TODAY()-H24<=30,"1-30 Days",IF(TODAY()-H24<=60,"31-60 Days",IF(TODAY()-H24<=90,"61-90 Days","90+ Days")))))))
E25: =IF(C25="","",_xlfn.XLOOKUP(C25,PONUMBER,POVENDORNAME)) | F25: =IF(E25="","",_xlfn.XLOOKUP(E25,Vendors!B$1:B$1048568,Vendors!A$1:A$1048568)) | G25: =IF(D25="","",_xlfn.XLOOKUP(F25,Vendors!A:A,Vendors!G:G)) | H25: =IF(B25="","",B25+G25) | I25: =IF(D25="","",SUMIF(Payments!C:C,A25,Payments!G:G)) | J25: =IF(D25="","",D25-I25) | K25: =IF(J25="","",IF(J25<=0,"Paid","Open")) | L25: =IF(J25="","",IF(J25<=0,0,MAX(0,TODAY()-B25))) | M25: =IF(J25="","",(IF(J25<=0,"Paid",IF(TODAY()<=H25,"Current",IF(TODAY()-H25<=30,"1-30 Days",IF(TODAY()-H25<=60,"31-60 Days",IF(TODAY()-H25<=90,"61-90 Days","90+ Days")))))))
E26: =IF(C26="","",_xlfn.XLOOKUP(C26,PONUMBER,POVENDORNAME)) | F26: =IF(E26="","",_xlfn.XLOOKUP(E26,Vendors!B$1:B$1048568,Vendors!A$1:A$1048568)) | G26: =IF(D26="","",_xlfn.XLOOKUP(F26,Vendors!A:A,Vendors!G:G)) | H26: =IF(B26="","",B26+G26) | I26: =IF(D26="","",SUMIF(Payments!C:C,A26,Payments!G:G)) | J26: =IF(D26="","",D26-I26) | K26: =IF(J26="","",IF(J26<=0,"Paid","Open")) | L26: =IF(J26="","",IF(J26<=0,0,MAX(0,TODAY()-B26))) | M26: =IF(J26="","",(IF(J26<=0,"Paid",IF(TODAY()<=H26,"Current",IF(TODAY()-H26<=30,"1-30 Days",IF(TODAY()-H26<=60,"31-60 Days",IF(TODAY()-H26<=90,"61-90 Days","90+ Days")))))))
E27: =IF(C27="","",_xlfn.XLOOKUP(C27,PONUMBER,POVENDORNAME)) | F27: =IF(E27="","",_xlfn.XLOOKUP(E27,Vendors!B$1:B$1048568,Vendors!A$1:A$1048568)) | G27: =IF(D27="","",_xlfn.XLOOKUP(F27,Vendors!A:A,Vendors!G:G)) | H27: =IF(B27="","",B27+G27) | I27: =IF(D27="","",SUMIF(Payments!C:C,A27,Payments!G:G)) | J27: =IF(D27="","",D27-I27) | K27: =IF(J27="","",IF(J27<=0,"Paid","Open")) | L27: =IF(J27="","",IF(J27<=0,0,MAX(0,TODAY()-B27))) | M27: =IF(J27="","",(IF(J27<=0,"Paid",IF(TODAY()<=H27,"Current",IF(TODAY()-H27<=30,"1-30 Days",IF(TODAY()-H27<=60,"31-60 Days",IF(TODAY()-H27<=90,"61-90 Days","90+ Days")))))))
E28: =IF(C28="","",_xlfn.XLOOKUP(C28,PONUMBER,POVENDORNAME)) | F28: =IF(E28="","",_xlfn.XLOOKUP(E28,Vendors!B$1:B$1048568,Vendors!A$1:A$1048568)) | G28: =IF(D28="","",_xlfn.XLOOKUP(F28,Vendors!A:A,Vendors!G:G)) | H28: =IF(B28="","",B28+G28) | I28: =IF(D28="","",SUMIF(Payments!C:C,A28,Payments!G:G)) | J28: =IF(D28="","",D28-I28) | K28: =IF(J28="","",IF(J28<=0,"Paid","Open")) | L28: =IF(J28="","",IF(J28<=0,0,MAX(0,TODAY()-B28))) | M28: =IF(J28="","",(IF(J28<=0,"Paid",IF(TODAY()<=H28,"Current",IF(TODAY()-H28<=30,"1-30 Days",IF(TODAY()-H28<=60,"31-60 Days",IF(TODAY()-H28<=90,"61-90 Days","90+ Days")))))))
E29: =IF(C29="","",_xlfn.XLOOKUP(C29,PONUMBER,POVENDORNAME)) | F29: =IF(E29="","",_xlfn.XLOOKUP(E29,Vendors!B$1:B$1048568,Vendors!A$1:A$1048568)) | G29: =IF(D29="","",_xlfn.XLOOKUP(F29,Vendors!A:A,Vendors!G:G)) | H29: =IF(B29="","",B29+G29) | I29: =IF(D29="","",SUMIF(Payments!C:C,A29,Payments!G:G)) | J29: =IF(D29="","",D29-I29) | K29: =IF(J29="","",IF(J29<=0,"Paid","Open")) | L29: =IF(J29="","",IF(J29<=0,0,MAX(0,TODAY()-B29))) | M29: =IF(J29="","",(IF(J29<=0,"Paid",IF(TODAY()<=H29,"Current",IF(TODAY()-H29<=30,"1-30 Days",IF(TODAY()-H29<=60,"31-60 Days",IF(TODAY()-H29<=90,"61-90 Days","90+ Days")))))))
E30: =IF(C30="","",_xlfn.XLOOKUP(C30,PONUMBER,POVENDORNAME)) | F30: =IF(E30="","",_xlfn.XLOOKUP(E30,Vendors!B$1:B$1048568,Vendors!A$1:A$1048568)) | G30: =IF(D30="","",_xlfn.XLOOKUP(F30,Vendors!A:A,Vendors!G:G)) | H30: =IF(B30="","",B30+G30) | I30: =IF(D30="","",SUMIF(Payments!C:C,A30,Payments!G:G)) | J30: =IF(D30="","",D30-I30) | K30: =IF(J30="","",IF(J30<=0,"Paid","Open")) | L30: =IF(J30="","",IF(J30<=0,0,MAX(0,TODAY()-B30))) | M30: =IF(J30="","",(IF(J30<=0,"Paid",IF(TODAY()<=H30,"Current",IF(TODAY()-H30<=30,"1-30 Days",IF(TODAY()-H30<=60,"31-60 Days",IF(TODAY()-H30<=90,"61-90 Days","90+ Days")))))))
E31: =IF(C31="","",_xlfn.XLOOKUP(C31,PONUMBER,POVENDORNAME)) | F31: =IF(E31="","",_xlfn.XLOOKUP(E31,Vendors!B$1:B$1048568,Vendors!A$1:A$1048568)) | G31: =IF(D31="","",_xlfn.XLOOKUP(F31,Vendors!A:A,Vendors!G:G)) | H31: =IF(B31="","",B31+G31) | I31: =IF(D31="","",SUMIF(Payments!C:C,A31,Payments!G:G)) | J31: =IF(D31="","",D31-I31) | K31: =IF(J31="","",IF(J31<=0,"Paid","Open")) | L31: =IF(J31="","",IF(J31<=0,0,MAX(0,TODAY()-B31))) | M31: =IF(J31="","",(IF(J31<=0,"Paid",IF(TODAY()<=H31,"Current",IF(TODAY()-H31<=30,"1-30 Days",IF(TODAY()-H31<=60,"31-60 Days",IF(TODAY()-H31<=90,"61-90 Days","90+ Days")))))))

Sheet Payments
A1: Payment ID | B1: Payment Date | C1: Invoice Number | D1: Purchase Order | E1: Vendor Name | F1: Vendor ID | G1: Payment Amount | H1: Payment Method | I1: Reference Number | J1: Notes
A2: PAY-0001 | B2: 46144 | C2: INV-46002 | D2: =IF(C2="","",_xlfn.XLOOKUP(C2,Invoices!A:A,Invoices!C:C)) -> PO-2026-1004 | E2: =IF(C2="","",_xlfn.XLOOKUP(C2,Invoices!A:A,Invoices!E:E)) -> ABC Office Supply | F2: =IF(C2="","",_xlfn.XLOOKUP(C2,Invoices!A:A,Invoices!F:F)) -> V001 | G2: 491.37 | H2: Check | I2: REF-80001
A3: PAY-0002 | B3: 46146 | C3: INV-46003 | D3: =IF(C3="","",_xlfn.XLOOKUP(C3,Invoices!A:A,Invoices!C:C)) -> PO-2026-1008 | E3: =IF(C3="","",_xlfn.XLOOKUP(C3,Invoices!A:A,Invoices!E:E)) -> ABC Office Supply | F3: =IF(C3="","",_xlfn.XLOOKUP(C3,Invoices!A:A,Invoices!F:F)) -> V001 | G3: 702.74 | H3: Credit Card | I3: REF-80002
A4: PAY-0003 | B4: 46143 | C4: INV-46004 | D4: =IF(C4="","",_xlfn.XLOOKUP(C4,Invoices!A:A,Invoices!C:C)) -> PO-2026-1008 | E4: =IF(C4="","",_xlfn.XLOOKUP(C4,Invoices!A:A,Invoices!E:E)) -> ABC Office Supply | F4: =IF(C4="","",_xlfn.XLOOKUP(C4,Invoices!A:A,Invoices!F:F)) -> V001 | G4: 700.69 | H4: ACH | I4: REF-80003
A5: PAY-0004 | B5: 46142 | C5: INV-46005 | D5: =IF(C5="","",_xlfn.XLOOKUP(C5,Invoices!A:A,Invoices!C:C)) -> PO-2026-1009 | E5: =IF(C5="","",_xlfn.XLOOKUP(C5,Invoices!A:A,Invoices!E:E)) -> XYZ Industrial Parts | F5: =IF(C5="","",_xlfn.XLOOKUP(C5,Invoices!A:A,Invoices!F:F)) -> V002 | G5: 562.74 | H5: ACH | I5: REF-80004
A6: PAY-0006 | B6: 46158 | C6: INV-46009 | D6: =IF(C6="","",_xlfn.XLOOKUP(C6,Invoices!A:A,Invoices!C:C)) -> PO-2026-1005 | E6: =IF(C6="","",_xlfn.XLOOKUP(C6,Invoices!A:A,Invoices!E:E)) -> Main Technology Services | F6: =IF(C6="","",_xlfn.XLOOKUP(C6,Invoices!A:A,Invoices!F:F)) -> V004 | G6: 300 | H6: Credit Card | I6: REF-80006
A7: PAY-0007 | B7: 46155 | C7: INV-46010 | D7: =IF(C7="","",_xlfn.XLOOKUP(C7,Invoices!A:A,Invoices!C:C)) -> PO-2026-1004 | E7: =IF(C7="","",_xlfn.XLOOKUP(C7,Invoices!A:A,Invoices!E:E)) -> ABC Office Supply | F7: =IF(C7="","",_xlfn.XLOOKUP(C7,Invoices!A:A,Invoices!F:F)) -> V001 | G7: 2182.33 | H7: ACH | I7: REF-80007
A8: PAY-0009 | B8: 46163 | C8: INV-46014 | D8: =IF(C8="","",_xlfn.XLOOKUP(C8,Invoices!A:A,Invoices!C:C)) -> PO-2026-1007 | E8: =IF(C8="","",_xlfn.XLOOKUP(C8,Invoices!A:A,Invoices!E:E)) -> U Packaging Inc | F8: =IF(C8="","",_xlfn.XLOOKUP(C8,Invoices!A:A,Invoices!F:F)) -> V003 | G8: 1500 | H8: Check | I8: REF-80009
A9: PAY-0010 | B9: 46170 | C9: INV-46015 | D9: =IF(C9="","",_xlfn.XLOOKUP(C9,Invoices!A:A,Invoices!C:C)) -> PO-2026-1006 | E9: =IF(C9="","",_xlfn.XLOOKUP(C9,Invoices!A:A,Invoices!E:E)) -> XYZ Industrial Parts | F9: =IF(C9="","",_xlfn.XLOOKUP(C9,Invoices!A:A,Invoices!F:F)) -> V002 | G9: 1000 | H9: Credit Card | I9: REF-80010
A10: PAY-0011 | B10: 46172 | C10: INV-46016 | D10: =IF(C10="","",_xlfn.XLOOKUP(C10,Invoices!A:A,Invoices!C:C)) -> PO-2026-1005 | E10: =IF(C10="","",_xlfn.XLOOKUP(C10,Invoices!A:A,Invoices!E:E)) -> Main Technology Services | F10: =IF(C10="","",_xlfn.XLOOKUP(C10,Invoices!A:A,Invoices!F:F)) -> V004 | G10: 500 | H10: ACH | I10: REF-80011
A11: PAY-0012 | B11: 46166 | C11: INV-46017 | D11: =IF(C11="","",_xlfn.XLOOKUP(C11,Invoices!A:A,Invoices!C:C)) -> PO-2026-1003 | E11: =IF(C11="","",_xlfn.XLOOKUP(C11,Invoices!A:A,Invoices!E:E)) -> U Packaging Inc | F11: =IF(C11="","",_xlfn.XLOOKUP(C11,Invoices!A:A,Invoices!F:F)) -> V003 | G11: 280 | H11: ACH | I11: REF-80012
A12: PAY-0012 | B12: 46230 | C12: INV-46018 | D12: =IF(C12="","",_xlfn.XLOOKUP(C12,Invoices!A:A,Invoices!C:C)) -> PO-2026-1010 | E12: =IF(C12="","",_xlfn.XLOOKUP(C12,Invoices!A:A,Invoices!E:E)) -> Water Street LLC | F12: =IF(C12="","",_xlfn.XLOOKUP(C12,Invoices!A:A,Invoices!F:F)) -> V005 | G12: 100 | H12: Check | I12: REF-80020
D13: =IF(C13="","",_xlfn.XLOOKUP(C13,Invoices!A:A,Invoices!C:C)) | E13: =IF(C13="","",_xlfn.XLOOKUP(C13,Invoices!A:A,Invoices!E:E)) | F13: =IF(C13="","",_xlfn.XLOOKUP(C13,Invoices!A:A,Invoices!F:F))
D14: =IF(C14="","",_xlfn.XLOOKUP(C14,Invoices!A:A,Invoices!C:C)) | E14: =IF(C14="","",_xlfn.XLOOKUP(C14,Invoices!A:A,Invoices!E:E)) | F14: =IF(C14="","",_xlfn.XLOOKUP(C14,Invoices!A:A,Invoices!F:F))
D15: =IF(C15="","",_xlfn.XLOOKUP(C15,Invoices!A:A,Invoices!C:C)) | E15: =IF(C15="","",_xlfn.XLOOKUP(C15,Invoices!A:A,Invoices!E:E)) | F15: =IF(C15="","",_xlfn.XLOOKUP(C15,Invoices!A:A,Invoices!F:F))
D16: =IF(C16="","",_xlfn.XLOOKUP(C16,Invoices!A:A,Invoices!C:C)) | E16: =IF(C16="","",_xlfn.XLOOKUP(C16,Invoices!A:A,Invoices!E:E)) | F16: =IF(C16="","",_xlfn.XLOOKUP(C16,Invoices!A:A,Invoices!F:F))
D17: =IF(C17="","",_xlfn.XLOOKUP(C17,Invoices!A:A,Invoices!C:C)) | E17: =IF(C17="","",_xlfn.XLOOKUP(C17,Invoices!A:A,Invoices!E:E)) | F17: =IF(C17="","",_xlfn.XLOOKUP(C17,Invoices!A:A,Invoices!F:F))
D18: =IF(C18="","",_xlfn.XLOOKUP(C18,Invoices!A:A,Invoices!C:C)) | E18: =IF(C18="","",_xlfn.XLOOKUP(C18,Invoices!A:A,Invoices!E:E)) | F18: =IF(C18="","",_xlfn.XLOOKUP(C18,Invoices!A:A,Invoices!F:F))
D19: =IF(C19="","",_xlfn.XLOOKUP(C19,Invoices!A:A,Invoices!C:C)) | E19: =IF(C19="","",_xlfn.XLOOKUP(C19,Invoices!A:A,Invoices!E:E)) | F19: =IF(C19="","",_xlfn.XLOOKUP(C19,Invoices!A:A,Invoices!F:F))
D20: =IF(C20="","",_xlfn.XLOOKUP(C20,Invoices!A:A,Invoices!C:C)) | E20: =IF(C20="","",_xlfn.XLOOKUP(C20,Invoices!A:A,Invoices!E:E)) | F20: =IF(C20="","",_xlfn.XLOOKUP(C20,Invoices!A:A,Invoices!F:F))
D21: =IF(C21="","",_xlfn.XLOOKUP(C21,Invoices!A:A,Invoices!C:C)) | E21: =IF(C21="","",_xlfn.XLOOKUP(C21,Invoices!A:A,Invoices!E:E)) | F21: =IF(C21="","",_xlfn.XLOOKUP(C21,Invoices!A:A,Invoices!F:F))
D22: =IF(C22="","",_xlfn.XLOOKUP(C22,Invoices!A:A,Invoices!C:C)) | E22: =IF(C22="","",_xlfn.XLOOKUP(C22,Invoices!A:A,Invoices!E:E)) | F22: =IF(C22="","",_xlfn.XLOOKUP(C22,Invoices!A:A,Invoices!F:F))
D23: =IF(C23="","",_xlfn.XLOOKUP(C23,Invoices!A:A,Invoices!C:C)) | E23: =IF(C23="","",_xlfn.XLOOKUP(C23,Invoices!A:A,Invoices!E:E)) | F23: =IF(C23="","",_xlfn.XLOOKUP(C23,Invoices!A:A,Invoices!F:F))

Sheet Vendors
A1: Vendor ID | B1: Vendor Name | C1: Category | D1: Contact Name | E1: Phone | F1: Email | G1: Net Days Due | H1: Preferred Vendor | I1: Tax ID | J1: Active | K1: Notes
A2: V001 | B2: ABC Office Supply | C2: Office Supplies | D2: John Jones | E2: (770) 555-0111 | F2: jjones@abcoffice.com | G2: 30 | H2: Yes | I2: 58-1001001 | J2: Yes
A3: V002 | B3: XYZ Industrial Parts | C3: Manufacturing Parts | D3: Sean Smith | E3: (678) 555-0112 | F3: ssmith@xyzindustrialparts.com | G3: 45 | H3: Yes | I3: 58-1001002 | J3: Yes
A4: V003 | B4: U Packaging Inc | C4: Packaging | D4: Mary Mayes | E4: (706) 555-0113 | F4: mmayes@upackaging.com | G4: 30 | H4: Yes | I4: 58-1001003 | J4: Yes
A5: V004 | B5: Main Technology Services | C5: IT Services | D5: Jane Johnson | E5: (470) 555-0114 | F5: janejohnson@maintech.com | G5: 15 | H5: No | I5: 58-1001004 | J5: Yes
A6: V005 | B6: Water Street LLC | C6: Cleaners | D6: Joe McPhee | E6: (770) 555-1215 | F6: jmcphee@waterstreet.com | G6: 30 | H6: No | I6: 58-1001005 | J6: Yes

Sheet Customer Invoice
A1: CUSTOMER INVOICE
A3: Main Company
A4: 123 Business Way • Gainesville, GA 30501 • (770) 555-0100
A6: Invoice Number | B6: INV-46007 | E6: Invoice Date | F6: =IF(B6="","",_xlfn.XLOOKUP(B6,Invoices!A:A,Invoices!B:B)) -> 46130
A8: Vendor Name | B8: =IF(B6="","",_xlfn.XLOOKUP(B6,Invoices!A:A,Invoices!E:E)) -> U Packaging Inc | E8: Vendor ID | F8: =IF(B6="","",_xlfn.XLOOKUP(B6,Invoices!A:A,Invoices!F:F)) -> V003
A10: PO Number | B10: =IF(B6="","",_xlfn.XLOOKUP(B6,Invoices!A:A,Invoices!C:C)) -> PO-2026-1007 | E10: Terms Net Days | F10: =IF(B6="","",_xlfn.XLOOKUP(B6,Invoices!A:A,Invoices!G:G)) -> 30
A12: Due Date | B12: =IF(B6="","",_xlfn.XLOOKUP(B6,Invoices!A:A,Invoices!H:H)) -> 46160 | E12: Approved By | F12: =IF(B6="","",_xlfn.XLOOKUP(B6,Invoices!A:A,Invoices!N:N)) -> Jordan Lee
A15: Line | B15: Description | C15: Quantity | D15: Unit Price | E15: Line Total | F15: Taxable | G15: Account | H15: Notes
A16: 1 | E16: =IF(OR(C16="",D16=""),0,C16*D16) -> 0
A17: 2 | E17: =IF(OR(C17="",D17=""),0,C17*D17) -> 0
A18: 3 | E18: =IF(OR(C18="",D18=""),0,C18*D18) -> 0
A19: 4 | E19: =IF(OR(C19="",D19=""),0,C19*D19) -> 0
A20: 5 | E20: =IF(OR(C20="",D20=""),0,C20*D20) -> 0
A21: 6 | E21: =IF(OR(C21="",D21=""),0,C21*D21) -> 0
A24: Notes / Terms: Thank you for your business. Please reference the invoice number with payment. | F24: Subtotal | G24: =SUM(E16:E21) -> 0
F25: Tax Rate | G25: 0
F26: Tax | G26: =SUMIF(F16:F21,"Yes",E16:E21)*G25 -> 0
F27: Total | G27: =G24+G26 -> 0
